atoz/__init__.py
atoz-0.0.1.dist-info/LICENSE.txt
atoz-0.0.1.dist-info/METADATA
atoz-0.0.1.dist-info/WHEEL
atoz-0.0.1.dist-info/top_level.txt
atoz-0.0.1.dist-info/RECORD
