Metadata-Version: 2.1
Name: atoz
Version: 0.0.1
Summary: A base utility
Home-page: https://github.com/skelethon/atoz
Author: skelethon
License: GPL-3.0
Download-URL: https://github.com/skelethon/atoz/downloads
Keywords: sysops,devops,toolkit
Platform: UNKNOWN
Requires-Python: >=2.7,!=3.0.*,!=3.1.*,!=3.2.*,!=3.3.*
